Workbook

Sheet Master
A2: Name of the LLP | B2: Daivbharathi Technologies LLP
A3: Address | B3: No 63, 1st Floor, 1st Main, 7th Block, Koramangala VI Block, Bangalore 560095
A4: LLPIN | B4: [To be provided]
A5: Period | B5: 2025-26
A6: PAN | B6: [To be provided]
A7: Financial Year Opening Date | B7: 45748
A8: Financial Year Closing Date | B8: 46112
A9: Previous Year Closing Date | B9: 45747
A10: Trial Balance period as per Tally (CY) | B10: 1-Apr-25 to 23-Mar-26
A11: Trial Balance period as per Tally (PY) | B11: 1-Apr-24 to 31-Mar-25
A13: Auditor's Name | B13: [To be provided]
A14: Designation | B14: [To be provided]
A15: Membership No. | B15: [To be provided]
A16: Audit Firm Name | B16: [To be provided]
A17: Firm Registration No. (FRN) | B17: [To be provided]
A18: UDIN | B18: [To be provided]
A19: Date (Auditor) | B19: [To be provided]
A20: Place (Auditor) | B20: [To be provided]
A22: Designated Partner 1 | B22: Samartha Raghava Nagabhushanam
A23: DPIN No. | B23: [To be provided]
... A27: DPIN No. | B27: [To be provided]
A28: Date | B28: =B24 -> [To be provided]
A29: Place | B29: [To be provided]
A31: Financials Rounded Off by | B31: 100
A32: Amount caption (derived) | B32: =IF(B31=100,"(Amount in ₹ '00)",IF(B31=1000,"(Amount in ₹ '000)",IF(B31=1,"(Amount in ₹)","(Amount in ₹ / "&B31&")"))) -> (Amount in ₹ '00)
A33: Current year column heading (derived) | B33: =UPPER(TEXT(B8,"mmmm d, yyyy")) -> MARCH 31, 2026
A34: Previous year column heading (derived) | B34: =UPPER(TEXT(B9,"mmmm d, yyyy")) -> MARCH 31, 2025
A36: PARTNERS' CAPITAL DETAILS (₹, as per Trial Balance)
A37: Partner | B37: Capital Account ledger (Tally) | C37: Contribution 31-Mar-26 (₹) | D37: Contribution 31-Mar-25 (₹) | E37: Profit sharing ratio (LLP Agreement)
A38: =B22 -> Samartha Raghava Nagabhushanam | B38: Samartha R .N -Captial Account | C38: =SUMIFS(TB!$D:$D,TB!$I:$I,"Partners Capital - Samartha R.N") -> 90000 | D38: =SUMIFS(TB!$F:$F,TB!$I:$I,"Partners Capital - Samartha R.N") -> 90000 | E38: [To be provided]
A39: =B26 -> [To be provided] | B39: No capital account in Trial Balance | C39: 0 | D39: 0 | E39: [To be provided]
A40: Total | C40: =SUM(C38:C39) -> 90000 | D40: =SUM(D38:D39) -> 90000
A42: Legend | B42: Yellow cells = information not available in the Trial Balance; to be filled in before finalisation. All other cells are as per the Tally Trial Balances or derived by formula.

Sheet TB
A1: =Master!B2 -> Daivbharathi Technologies LLP
A2: Trial Balance (closing balances as per Tally) - mapping to Financial Statements
A3: ="Current year: "&Master!B10&" | Previous year: "&Master!B11 -> Current year: 1-Apr-25 to 23-Mar-26 | Previous year: 1-Apr-24 to 31-Mar-25
A4: Totals of rows 7 to 75 (insert new ledger rows above row 76) | C4: =SUM(C7:C76) -> 4380402.5 | D4: =SUM(D7:D76) -> 4380402.5 | E4: =SUM(E7:E76) -> 1133680 | F4: =SUM(F7:F76) -> 1133680 | G4: =SUM(G7:G76) -> 87608.05 | H4: =SUM(H7:H76) -> 22673.6
C5: 2025-26 (₹) - as per Tally | E5: 2024-25 (₹) - as per Tally | G5: Rounded Off (÷ Master!B31)
A6: Particulars (Tally ledger) | B6: Tally Group | C6: Debit | D6: Credit | E6: Debit | F6: Credit | G6: Amount CY | H6: Amount PY | I6: Grouping (key used by Notes) | J6: Head (Financial Statement caption)
A7: Samartha R .N -Captial Account | B7: Capital Account / Partners Capital | D7: 90000 | F7: 90000 | G7: =(C7+D7)/Master!$B$31 -> 900 | H7: =(E7+F7)/Master!$B$31 -> 900 | I7: Partners Capital - Samartha R.N | J7: Partners' capital
A8: Manasa | B8: Loans (Liability) / Unsecured Loans | D8: 170180 | G8: =(C8+D8)/Master!$B$31 -> 1701.8 | H8: =(E8+F8)/Master!$B$31 -> 0 | I8: Loan - Manasa | J8: Long-term borrowings
A9: Samartha Raghava NAgabhushanam-Loan | B9: Loans (Liability) / Unsecured Loans | D9: 2480680 | F9: 780680 | G9: =(C9+D9)/Master!$B$31 -> 24806.8 | H9: =(E9+F9)/Master!$B$31 -> 7806.8 | I9: Loan - Samartha Raghava Nagabhushanam | J9: Long-term borrowings
A10: 194 J-TDS on Profession | B10: Current Liabilities / Duties & Taxes | D10: 21760 | F10: 35000 | G10: =(C10+D10)/Master!$B$31 -> 217.6 | H10: =(E10+F10)/Master!$B$31 -> 350 | I10: TDS Payable 194J | J10: Other current liabilities
A11: GST Payable | B11: Current Liabilities / Duties & Taxes | D11: 7505.41 | G11: =(C11+D11)/Master!$B$31 -> 75.0541 | H11: =(E11+F11)/Master!$B$31 -> 0 | I11: GST Payable | J11: Other current liabilities
A12: Input 9 % SGST | B12: Current Liabilities / Duties & Taxes | C12: 2820.94 | G12: =(C12+D12)/Master!$B$31 -> 28.2094 | H12: =(E12+F12)/Master!$B$31 -> 0 | I12: Input SGST | J12: Other current assets
A13: Input CGST 9% | B13: Current Liabilities / Duties & Taxes | C13: 2820.94 | G13: =(C13+D13)/Master!$B$31 -> 28.2094 | H13: =(E13+F13)/Master!$B$31 -> 0 | I13: Input CGST | J13: Other current assets
A14: Ajay Pandey | B14: Current Liabilities / Sundry Creditors | D14: 30800 | G14: =(C14+D14)/Master!$B$31 -> 308 | H14: =(E14+F14)/Master!$B$31 -> 0 | I14: Trade Payables - Others | J14: Trade payables
A15: Bhadri Narayan | B15: Current Liabilities / Sundry Creditors | D15: 8606.5 | G15: =(C15+D15)/Master!$B$31 -> 86.065 | H15: =(E15+F15)/Master!$B$31 -> 0 | I15: Trade Payables - Others | J15: Trade payables
A16: Bharti Airtel Limited | B16: Current Liabilities / Sundry Creditors | D16: 6339.78 | G16: =(C16+D16)/Master!$B$31 -> 63.3978 | H16: =(E16+F16)/Master!$B$31 -> 0 | I16: Trade Payables - Others | J16: Trade payables
A17: Dhakshayani | B17: Current Liabilities / Sundry Creditors | D17: 3000 | G17: =(C17+D17)/Master!$B$31 -> 30 | H17: =(E17+F17)/Master!$B$31 -> 0 | I17: Trade Payables - Others | J17: Trade payables
A18: Dhanush | B18: Current Liabilities / Sundry Creditors | D18: 8815 | G18: =(C18+D18)/Master!$B$31 -> 88.15 | H18: =(E18+F18)/Master!$B$31 -> 0 | I18: Trade Payables - Others | J18: Trade payables
A19: Face Book India Online Services Private Limited | B19: Current Liabilities / Sundry Creditors | D19: 163951.21 | G19: =(C19+D19)/Master!$B$31 -> 1639.5121 | H19: =(E19+F19)/Master!$B$31 -> 0 | I19: Trade Payables - Others | J19: Trade payables
A20: Google India Private Limited | B20: Current Liabilities / Sundry Creditors | D20: 3657.53 | G20: =(C20+D20)/Master!$B$31 -> 36.5753 | H20: =(E20+F20)/Master!$B$31 -> 0 | I20: Trade Payables - Others | J20: Trade payables
A21: J R Computers Inc | B21: Current Liabilities / Sundry Creditors | D21: 9263 | G21: =(C21+D21)/Master!$B$31 -> 92.63 | H21: =(E21+F21)/Master!$B$31 -> 0 | I21: Trade Payables - Others | J21: Trade payables
A22: Karnataka Digital Studio | B22: Current Liabilities / Sundry Creditors | D22: 5400 | G22: =(C22+D22)/Master!$B$31 -> 54 | H22: =(E22+F22)/Master!$B$31 -> 0 | I22: Trade Payables - Others | J22: Trade payables
A23: K Soorya | B23: Current Liabilities / Sundry Creditors | D23: 33930 | G23: =(C23+D23)/Master!$B$31 -> 339.3 | H23: =(E23+F23)/Master!$B$31 -> 0 | I23: Trade Payables - Others | J23: Trade payables
A24: Madhavi K | B24: Current Liabilities / Sundry Creditors | D24: 90000 | G24: =(C24+D24)/Master!$B$31 -> 900 | H24: =(E24+F24)/Master!$B$31 -> 0 | I24: Trade Payables - Others | J24: Trade payables
A25: Manjunath N | B25: Current Liabilities / Sundry Creditors | D25: 5000 | G25: =(C25+D25)/Master!$B$31 -> 50 | H25: =(E25+F25)/Master!$B$31 -> 0 | I25: Trade Payables - Others | J25: Trade payables
... A32: Usha Devi | B32: Current Liabilities / Sundry Creditors | D32: 22500 | G32: =(C32+D32)/Master!$B$31 -> 225 | H32: =(E32+F32)/Master!$B$31 -> 0 | I32: Trade Payables - Others | J32: Trade payables
A33: Venkatesh | B33: Current Liabilities / Sundry Creditors | D33: 16528 | F33: 67500 | G33: =(C33+D33)/Master!$B$31 -> 165.28 | H33: =(E33+F33)/Master!$B$31 -> 675 | I33: Trade Payables - Others | J33: Trade payables
A34: Vinyas Kumar | B34: Current Liabilities / Sundry Creditors | D34: 18982 | G34: =(C34+D34)/Master!$B$31 -> 189.82 | H34: =(E34+F34)/Master!$B$31 -> 0 | I34: Trade Payables - Others | J34: Trade payables
A35: B Omkarmurthy | B35: Current Liabilities / Sundry Creditors | F35: 3000 | G35: =(C35+D35)/Master!$B$31 -> 0 | H35: =(E35+F35)/Master!$B$31 -> 30 | I35: Trade Payables - Others | J35: Trade payables
A36: Medha Sudarshan | B36: Current Liabilities / Sundry Creditors | F36: 90000 | G36: =(C36+D36)/Master!$B$31 -> 0 | H36: =(E36+F36)/Master!$B$31 -> 900 | I36: Trade Payables - Others | J36: Trade payables
A37: Sudhakar | B37: Current Liabilities / Sundry Creditors | F37: 67500 | G37: =(C37+D37)/Master!$B$31 -> 0 | H37: =(E37+F37)/Master!$B$31 -> 675 | I37: Trade Payables - Others | J37: Trade payables
A38: Mangala | B38: Current Liabilities / Sundry Creditors (Dr balance) | C38: 15000 | G38: =(C38+D38)/Master!$B$31 -> 150 | H38: =(E38+F38)/Master!$B$31 -> 0 | I38: Advance - Mangala | J38: Short-term loans and advances
A39: Sriguru P V | B39: Current Liabilities / Sundry Creditors (Dr balance) | C39: 20000 | G39: =(C39+D39)/Master!$B$31 -> 200 | H39: =(E39+F39)/Master!$B$31 -> 0 | I39: Advance - Sriguru P V | J39: Short-term loans and advances
A40: Subodh Kumar Mishra | B40: Current Liabilities / Sundry Creditors (Dr balance) | C40: 121000 | G40: =(C40+D40)/Master!$B$31 -> 1210 | H40: =(E40+F40)/Master!$B$31 -> 0 | I40: Advance - Subodh Kumar Mishra | J40: Short-term loans and advances
A41: Swami Gangaram | B41: Current Liabilities / Sundry Creditors (Dr balance) | C41: 2500 | G41: =(C41+D41)/Master!$B$31 -> 25 | H41: =(E41+F41)/Master!$B$31 -> 0 | I41: Advance - Swami Gangaram | J41: Short-term loans and advances
A42: Yuvaraj | B42: Current Liabilities / Sundry Creditors (Dr balance) | C42: 15000 | G42: =(C42+D42)/Master!$B$31 -> 150 | H42: =(E42+F42)/Master!$B$31 -> 0 | I42: Advance - Yuvaraj | J42: Short-term loans and advances
A43: Cash | B43: Current Assets / Cash-in-Hand | C43: 20754.2 | G43: =(C43+D43)/Master!$B$31 -> 207.542 | H43: =(E43+F43)/Master!$B$31 -> 0 | I43: Cash in hand | J43: Cash and cash equivalents
A44: Kotak Mahindra Bank (Dr balance) | B44: Current Assets / Bank Accounts | E44: 12768.48 | G44: =(C44+D44)/Master!$B$31 -> 0 | H44: =(E44+F44)/Master!$B$31 -> 127.6848 | I44: Bank - Kotak Mahindra Bank | J44: Cash and cash equivalents
A45: Kotak Mahindra Bank (Cr balance - book overdraft) | B45: Current Assets / Bank Accounts | D45: 2593.05 | G45: =(C45+D45)/Master!$B$31 -> 25.9305 | H45: =(E45+F45)/Master!$B$31 -> 0 | I45: Book overdraft - Kotak Mahindra Bank | J45: Other current liabilities
A46: B2C Sales | B46: Sales Accounts | D46: 1059363.5 | G46: =(C46+D46)/Master!$B$31 -> 10593.635 | H46: =(E46+F46)/Master!$B$31 -> 0 | I46: B2C Sales | J46: Revenue from operations
A47: Accomodation and Hotel Expenses | B47: Indirect Expenses | C47: 17510 | G47: =(C47+D47)/Master!$B$31 -> 175.1 | H47: =(E47+F47)/Master!$B$31 -> 0 | I47: Accomodation and Hotel Expenses | J47: Other expenses
A48: Advertisement Campaining Cost IGST | B48: Indirect Expenses | C48: 410685.35 | G48: =(C48+D48)/Master!$B$31 -> 4106.8535 | H48: =(E48+F48)/Master!$B$31 -> 0 | I48: Advertisement Campaining Cost IGST | J48: Other expenses
A49: Bank Charges | B49: Indirect Expenses | C49: 880.63 | E49: 311.52 | G49: =(C49+D49)/Master!$B$31 -> 8.8063 | H49: =(E49+F49)/Master!$B$31 -> 3.1152 | I49: Bank Charges | J49: Other expenses
A50: Branding Expenses | B50: Indirect Expenses | C50: 19100 | G50: =(C50+D50)/Master!$B$31 -> 191 | H50: =(E50+F50)/Master!$B$31 -> 0 | I50: Branding Expenses | J50: Other expenses
A51: Conveyance | B51: Indirect Expenses | C51: 25373 | G51: =(C51+D51)/Master!$B$31 -> 253.73 | H51: =(E51+F51)/Master!$B$31 -> 0 | I51: Conveyance | J51: Other expenses
A52: Data Infrastructure (GST) | B52: Indirect Expenses | C52: 26223.64 | G52: =(C52+D52)/Master!$B$31 -> 262.2364 | H52: =(E52+F52)/Master!$B$31 -> 0 | I52: Data Infrastructure (GST) | J52: Other expenses
A53: Design and Development | B53: Indirect Expenses | C53: 70000 | G53: =(C53+D53)/Master!$B$31 -> 700 | H53: =(E53+F53)/Master!$B$31 -> 0 | I53: Design and Development | J53: Other expenses
A54: Employer Professional Tax | B54: Indirect Expenses | E54: 2500 | G54: =(C54+D54)/Master!$B$31 -> 0 | H54: =(E54+F54)/Master!$B$31 -> 25 | I54: Employer Professional Tax | J54: Other expenses
A55: GST Late File Fees | B55: Indirect Expenses | C55: 20 | G55: =(C55+D55)/Master!$B$31 -> 0.2 | H55: =(E55+F55)/Master!$B$31 -> 0 | I55: GST Late File Fees | J55: Other expenses
A56: Interest on TDS | B56: Indirect Expenses | C56: 2164 | E56: 780 | G56: =(C56+D56)/Master!$B$31 -> 21.64 | H56: =(E56+F56)/Master!$B$31 -> 7.8 | I56: Interest on TDS | J56: Other expenses
A57: Internship Charges | B57: Indirect Expenses | C57: 12000 | G57: =(C57+D57)/Master!$B$31 -> 120 | H57: =(E57+F57)/Master!$B$31 -> 0 | I57: Internship Charges | J57: Other expenses
A58: Local Travel and Conveyance | B58: Indirect Expenses | C58: 177417 | G58: =(C58+D58)/Master!$B$31 -> 1774.17 | H58: =(E58+F58)/Master!$B$31 -> 0 | I58: Local Travel and Conveyance | J58: Other expenses
A59: Mobile and Telepohone Exenses | B59: Indirect Expenses | C59: 9871.95 | G59: =(C59+D59)/Master!$B$31 -> 98.7195 | H59: =(E59+F59)/Master!$B$31 -> 0 | I59: Mobile and Telepohone Exenses | J59: Other expenses
A60: Office Expenses | B60: Indirect Expenses | C60: 80518 | G60: =(C60+D60)/Master!$B$31 -> 805.18 | H60: =(E60+F60)/Master!$B$31 -> 0 | I60: Office Expenses | J60: Other expenses
A61: Payment Gate Way Comm. GST Exmt | B61: Indirect Expenses | C61: 2535.68 | G61: =(C61+D61)/Master!$B$31 -> 25.3568 | H61: =(E61+F61)/Master!$B$31 -> 0 | I61: Payment Gate Way Comm. GST Exmt | J61: Other expenses
A62: Payment Gate Way Commission | B62: Indirect Expenses | C62: 24901.09 | G62: =(C62+D62)/Master!$B$31 -> 249.0109 | H62: =(E62+F62)/Master!$B$31 -> 0 | I62: Payment Gate Way Commission | J62: Other expenses
A63: Pooja Expenses | B63: Indirect Expenses | C63: 959127.5 | G63: =(C63+D63)/Master!$B$31 -> 9591.275 | H63: =(E63+F63)/Master!$B$31 -> 0 | I63: Pooja Expenses | J63: Other expenses
A64: Postage and Courier Expenses | B64: Indirect Expenses | C64: 24538 | G64: =(C64+D64)/Master!$B$31 -> 245.38 | H64: =(E64+F64)/Master!$B$31 -> 0 | I64: Postage and Courier Expenses | J64: Other expenses
A65: Preincorporation Expenses | B65: Indirect Expenses | C65: 36000 | E65: 479320 | G65: =(C65+D65)/Master!$B$31 -> 360 | H65: =(E65+F65)/Master!$B$31 -> 4793.2 | I65: Preincorporation Expenses | J65: Other expenses
A66: Printing Charges | B66: Indirect Expenses | C66: 43036 | G66: =(C66+D66)/Master!$B$31 -> 430.36 | H66: =(E66+F66)/Master!$B$31 -> 0 | I66: Printing Charges | J66: Other expenses
A67: Professional Charges | B67: Indirect Expenses | C67: 1008252 | E67: 450000 | G67: =(C67+D67)/Master!$B$31 -> 10082.52 | H67: =(E67+F67)/Master!$B$31 -> 4500 | I67: Professional Charges | J67: Other expenses
A68: R O C and Filing Expenses | B68: Indirect Expenses | E68: 35000 | G68: =(C68+D68)/Master!$B$31 -> 0 | H68: =(E68+F68)/Master!$B$31 -> 350 | I68: R O C and Filing Expenses | J68: Other expenses
A69: Round Off | B69: Indirect Expenses | C69: 0.04 | G69: =(C69+D69)/Master!$B$31 -> 0.0004 | H69: =(E69+F69)/Master!$B$31 -> 0 | I69: Round Off | J69: Other expenses
A70: Staff Welfare | B70: Indirect Expenses | C70: 7681 | G70: =(C70+D70)/Master!$B$31 -> 76.81 | H70: =(E70+F70)/Master!$B$31 -> 0 | I70: Staff Welfare | J70: Other expenses
A71: Studio Expenses (GST 0%) | B71: Indirect Expenses | C71: 24000 | E71: 28000 | G71: =(C71+D71)/Master!$B$31 -> 240 | H71: =(E71+F71)/Master!$B$31 -> 280 | I71: Studio Expenses (GST 0%) | J71: Other expenses
A72: Subscrptions Expenses | B72: Indirect Expenses | C72: 15000 | G72: =(C72+D72)/Master!$B$31 -> 150 | H72: =(E72+F72)/Master!$B$31 -> 0 | I72: Subscrptions Expenses | J72: Other expenses
A73: Translation Expenses | B73: Indirect Expenses | C73: 52760 | G73: =(C73+D73)/Master!$B$31 -> 527.6 | H73: =(E73+F73)/Master!$B$31 -> 0 | I73: Translation Expenses | J73: Other expenses
A74: Web Site Development Expenses | B74: Indirect Expenses | C74: 10000 | E74: 125000 | G74: =(C74+D74)/Master!$B$31 -> 100 | H74: =(E74+F74)/Master!$B$31 -> 1250 | I74: Web Site Development Expenses | J74: Other expenses
A75: Profit & Loss A/c (opening balance - accumulated loss brought forward) | B75: Profit & Loss A/c | C75: 1120911.5 | G75: =(C75+D75)/Master!$B$31 -> 11209.115 | H75: =(E75+F75)/Master!$B$31 -> 0 | I75: Opening P&L | J75: Reserves and surplus
A77: Grand Total as per Tally Trial Balance | C77: 4380402.5 | D77: 4380402.5 | E77: 1133680 | F77: 1133680
A78: Difference: mapped total less Tally Grand Total (must be nil) | C78: =C4-C77 -> 0 | D78: =D4-D77 -> 0 | E78: =E4-E77 -> 0 | F78: =F4-F77 -> 0
A79: Difference: Debit less Credit (must be nil) | C79: =C4-D4 -> 0 | E79: =E4-F4 -> 0

Sheet BS
A1: =UPPER(Master!B2) -> DAIVBHARATHI TECHNOLOGIES LLP
A2: ="LLPIN: "&UPPER(Master!B4) -> LLPIN: [TO BE PROVIDED]
A3: =Master!B3 -> No 63, 1st Floor, 1st Main, 7th Block, Koramangala VI Block, Bangalore 560095
A4: ="BALANCE SHEET AS AT "&Master!B33 -> BALANCE SHEET AS AT MARCH 31, 2026
E5: =Master!B32 -> (Amount in ₹ '00)
A6: PARTICULARS | C6: NOTE | D6: =Master!B33 -> MARCH 31, 2026 | E6: =Master!B34 -> MARCH 31, 2025 | G6: Check (outside print area)
A7: LIABILITIES | G7: ="Total Liabilities less Total Assets (CY): "&TEXT(D19-D31,"#,##0.00") -> Total Liabilities less Total Assets (CY): 0.00
A8: Partners' funds | G8: ="Total Liabilities less Total Assets (PY): "&TEXT(E19-E31,"#,##0.00") -> Total Liabilities less Total Assets (PY): 0.00
A9: (a) Partners' capital | C9: 2.1 | D9: ='2.1'!D13 -> 900 | E9: ='2.1'!E13 -> 900
A10: (b) Reserves and surplus | C10: 2.2 | D10: ='2.2 - 2.10'!D15 -> -31211.429 | E10: ='2.2 - 2.10'!E15 -> -11209.115
A11: Total Partners' funds | D11: =SUM(D9:D10) -> -30311.429 | E11: =SUM(E9:E10) -> -10309.115
A12: Non-current liabilities
A13: (a) Long-term borrowings | C13: 2.3 | D13: ='2.2 - 2.10'!D22 -> 26508.6 | E13: ='2.2 - 2.10'!E22 -> 7806.8
A14: Total Non-current liabilities | D14: =SUM(D13:D13) -> 26508.6 | E14: =SUM(E13:E13) -> 7806.8
A15: Current Liabilities
A16: (a) Trade payables | C16: 2.4 | D16: ='2.2 - 2.10'!D30 -> 5483.2048 | E16: ='2.2 - 2.10'!E30 -> 2280
A17: (b) Other current liabilities | C17: 2.5 | D17: ='2.2 - 2.10'!D39 -> 318.5846 | E17: ='2.2 - 2.10'!E39 -> 350
A18: Total Current Liabilities | D18: =SUM(D16:D17) -> 5801.7894 | E18: =SUM(E16:E17) -> 2630
A19: TOTAL LIABILITIES | D19: =D11+D14+D18 -> 1998.9608 | E19: =E11+E14+E18 -> 127.6848
A21: ASSETS
A22: Non-current assets
A23: (a) Property, Plant & Equipment & Intangible assets
A24: (i) Property, Plant & Equipment | D24: 0 | E24: 0
A25: ="Total "&A22 -> Total Non-current assets | D25: =SUM(D24:D24) -> 0 | E25: =SUM(E24:E24) -> 0
A26: Current assets
A27: (a) Cash and cash equivalents | C27: 2.6 | D27: ='2.2 - 2.10'!D45 -> 207.542 | E27: ='2.2 - 2.10'!E45 -> 127.6848
A28: (b) Short-term loans and advances | C28: 2.7 | D28: ='2.2 - 2.10'!D55 -> 1735 | E28: ='2.2 - 2.10'!E55 -> 0
A29: (c) Other current assets | C29: 2.8 | D29: ='2.2 - 2.10'!D62 -> 56.4188 | E29: ='2.2 - 2.10'!E62 -> 0
A30: ="Total "&A26 -> Total Current assets | D30: =SUM(D27:D29) -> 1998.9608 | E30: =SUM(E27:E29) -> 127.6848
A31: =UPPER("Total "&A21) -> TOTAL ASSETS | D31: =D25+D30 -> 1998.9608 | E31: =E25+E30 -> 127.6848
A33: SIGNIFICANT ACCOUNTING POLICIES, NOTES FORMING PART OF THE FINANCIAL STATEMENTS | C33: 1 & 2
A35: As per our report attached | B35: For and on behalf of the Partners of
A36: ="For "&Master!B16 -> For [To be provided] | B36: =Master!B2 -> Daivbharathi Technologies LLP
A37: ="(FRN: "&Master!B17&")" -> (FRN: [To be provided])
A41: =UPPER(Master!B13) -> [TO BE PROVIDED] | B41: =UPPER(Master!B22) -> SAMARTHA RAGHAVA NAGABHUSHANAM | D41: =UPPER(Master!B26) -> [TO BE PROVIDED]
A42: =PROPER(Master!B14) -> [To Be Provided] | B42: Designated Partner | D42: =B42 -> Designated Partner
A43: ="Membership No. "&Master!B15 -> Membership No. [To be provided] | B43: ="DPIN: "&Master!B23 -> DPIN: [To be provided] | D43: ="DPIN: "&Master!B27 -> DPIN: [To be provided]
A44: ="UDIN: "&Master!B18 -> UDIN: [To be provided]
A45: =Master!B19 -> [To be provided] | B45: =Master!B24 -> [To be provided] | D45: =Master!B28 -> [To be provided]
A46: =Master!B20 -> [To be provided] | B46: =Master!B25 -> [To be provided] | D46: =Master!B29 -> [To be provided]

Sheet PL
A1: =UPPER(Master!B2) -> DAIVBHARATHI TECHNOLOGIES LLP
A2: ="LLPIN: "&UPPER(Master!B4) -> LLPIN: [TO BE PROVIDED]
A3: =Master!B3 -> No 63, 1st Floor, 1st Main, 7th Block, Koramangala VI Block, Bangalore 560095
A4: ="PROFIT AND LOSS STATEMENT FOR THE PERIOD "&Master!B5 -> PROFIT AND LOSS STATEMENT FOR THE PERIOD 2025-26
E5: =Master!B32 -> (Amount in ₹ '00)
A6: PARTICULARS | C6: NOTE | D6: =Master!B33 -> MARCH 31, 2026 | E6: =Master!B34 -> MARCH 31, 2025
A7: REVENUE
A8: (a) Revenue from operations | C8: 2.9 | D8: ='2.2 - 2.10'!D68 -> 10593.635 | E8: ='2.2 - 2.10'!E68 -> 0
A9: (b) Other income | D9: 0 | E9: 0
A10: Total Income | D10: =SUM(D8:D9) -> 10593.635 | E10: =SUM(E8:E9) -> 0
A12: EXPENSES
A13: (A) Other expenses | C13: 2.10 | D13: ='2.2 - 2.10'!D105 -> 30595.949 | E13: ='2.2 - 2.10'!E105 -> 11209.115
A14: Total Expenses | D14: =SUM(D13:D13) -> 30595.949 | E14: =SUM(E13:E13) -> 11209.115
A16: Profit/(Loss) before exceptional & extraordinary items and tax | D16: =D10-D14 -> -20002.313 | E16: =E10-E14 -> -11209.115
A17: Exceptional items | D17: 0 | E17: 0
A18: Profit/(Loss) before extraordinary items and tax | D18: =D16-D17 -> -20002.313 | E18: =E16-E17 -> -11209.115
A19: Extraordinary items | D19: 0 | E19: 0
A20: Profit/(Loss) before tax | D20: =D18+D19 -> -20002.313 | E20: =E18+E19 -> -11209.115
A22: Tax Expenses
A23: (a) Current Tax | D23: 0 | E23: 0
A24: (b) Deferred Tax Charge/(Credit) | D24: 0 | E24: 0
A25: Total tax expenses | D25: =SUM(D23:D24) -> 0 | E25: =SUM(E23:E24) -> 0
A27: Profit/(Loss) after tax | D27: =D20-D25 -> -20002.313 | E27: =E20-E25 -> -11209.115
A29: SIGNIFICANT ACCOUNTING POLICIES, NOTES FORMING PART OF THE FINANCIAL STATEMENTS | C29: 1 & 2
A31: As per our report attached | B31: For and on behalf of the Partners of
A32: ="For "&Master!B16 -> For [To be provided] | B32: =Master!B2 -> Daivbharathi Technologies LLP
A33: ="(FRN: "&Master!B17&")" -> (FRN: [To be provided])
A37: =UPPER(Master!B13) -> [TO BE PROVIDED] | B37: =UPPER(Master!B22) -> SAMARTHA RAGHAVA NAGABHUSHANAM | D37: =UPPER(Master!B26) -> [TO BE PROVIDED]
A38: =PROPER(Master!B14) -> [To Be Provided] | B38: Designated Partner | D38: =B38 -> Designated Partner
A39: ="Membership No. "&Master!B15 -> Membership No. [To be provided] | B39: ="DPIN: "&Master!B23 -> DPIN: [To be provided] | D39: ="DPIN: "&Master!B27 -> DPIN: [To be provided]
A40: ="UDIN: "&Master!B18 -> UDIN: [To be provided]
A41: =Master!B19 -> [To be provided] | B41: =Master!B24 -> [To be provided] | D41: =Master!B28 -> [To be provided]
A42: =Master!B20 -> [To be provided] | B42: =Master!B25 -> [To be provided] | D42: =Master!B29 -> [To be provided]

Sheet 2.1
A1: =UPPER(Master!B2) -> DAIVBHARATHI TECHNOLOGIES LLP | F1: Grouping keys (outside print area)
A2: ="LLPIN: "&UPPER(Master!B4) -> LLPIN: [TO BE PROVIDED]
A3: =Master!B3 -> No 63, 1st Floor, 1st Main, 7th Block, Koramangala VI Block, Bangalore 560095
A4: ="2. NOTES FORMING PART OF THE FINANCIAL STATEMENTS FOR THE YEAR ENDED "&Master!B33 -> 2. NOTES FORMING PART OF THE FINANCIAL STATEMENTS FOR THE YEAR ENDED MARCH 31, 2026
A6: 2.1 Partners' capital
A8: (A) Statement Showing Partners' Capital Contribution | E8: =Master!B32 -> (Amount in ₹ '00)
A9: PARTICULARS | D9: =Master!B33 -> MARCH 31, 2026 | E9: =Master!B34 -> MARCH 31, 2025
A10: Capital contribution by partners
A11: =Master!B22 -> Samartha Raghava Nagabhushanam | D11: =SUMIFS(TB!$G:$G,TB!$I:$I,$F11) -> 900 | E11: =SUMIFS(TB!$H:$H,TB!$I:$I,$F11) -> 900 | F11: Partners Capital - Samartha R.N
A12: =Master!B26 -> [To be provided] | D12: 0 | E12: 0
A13: Total | D13: =SUM(D11:D12) -> 900 | E13: =SUM(E11:E12) -> 900
A15: (B) Reconciliation Of Partners' Capital At The Beginning And At The End Of The Reporting Period | E15: =Master!B32 -> (Amount in ₹ '00)
A16: PARTICULARS | D16: =Master!B33 -> MARCH 31, 2026 | E16: =Master!B34 -> MARCH 31, 2025
A17: Balance at the beginning of the year | D17: =E19 -> 900 | E17: 0
A18: Add: Capital contributed during the year | D18: =D19-D17 -> 0 | E18: =E19-E17 -> 900
A19: Balance at the end of the year | D19: =D13 -> 900 | E19: =E13 -> 900
A21: (C) Terms Of Partnership:
A22: The rights and obligations of the partners, their capital contribution and the profit sharing ratio are governed by the LLP Agreement. No interest on partners' capital and no remuneration to partners has been charged to the Statement of Profit and Loss for the year (previous year: Nil), as no such ledgers appear in the books of account.
A24: (D) Details Of Partners And Their Capital Contribution:
A25: PARTICULARS | D25: =Master!B33 -> MARCH 31, 2026 | E25: =Master!B34 -> MARCH 31, 2025
D26: Contribution | E26: Contribution
A27: =A11 -> Samartha Raghava Nagabhushanam | D27: =D11 -> 900 | E27: =E11 -> 900
A28: =A12 -> [To be provided] | D28: =D12 -> 0 | E28: =E12 -> 0
A29: Total | D29: =SUM(D27:D28) -> 900 | E29: =SUM(E27:E28) -> 900
A30: % of total contribution | D30: =IF(D29=0,0,D27/D29) -> 1 | E30: =IF(E29=0,0,E27/E29) -> 1

Sheet 2.2 - 2.10
A1: Grouping keys (column A is outside the print area) | B1: =UPPER(Master!B2) -> DAIVBHARATHI TECHNOLOGIES LLP
B2: ="LLPIN: "&UPPER(Master!B4) -> LLPIN: [TO BE PROVIDED]
B3: =Master!B3 -> No 63, 1st Floor, 1st Main, 7th Block, Koramangala VI Block, Bangalore 560095
B4: ="2. NOTES FORMING PART OF THE FINANCIAL STATEMENTS FOR THE YEAR ENDED "&Master!B33 -> 2. NOTES FORMING PART OF THE FINANCIAL STATEMENTS FOR THE YEAR ENDED MARCH 31, 2026
E5: =Master!B32 -> (Amount in ₹ '00)
B6: NOTE | C6: PARTICULARS | D6: =Master!B33 -> MARCH 31, 2026 | E6: =Master!B34 -> MARCH 31, 2025
B8: 2.2 | C8: Reserves and surplus
C10: Surplus / (deficit) - balance in the statement of profit and loss account
A11: Opening P&L | C11: Opening Balance | D11: =-SUMIFS(TB!$G:$G,TB!$I:$I,$A11) -> -11209.115 | E11: =-SUMIFS(TB!$H:$H,TB!$I:$I,$A11) -> 0
C12: Add: Profit/ (Loss) for the year | D12: =PL!D27 -> -20002.313 | E12: =PL!E27 -> -11209.115
C13: Less: Amount utilised | D13: 0 | E13: 0
C14: Less: Transfer to reserves | D14: 0 | E14: 0
C15: Closing Balance | D15: =D11+D12-D13-D14 -> -31211.429 | E15: =E11+E12-E13-E14 -> -11209.115
D16: =D15 -> -31211.429 | E16: =E15 -> -11209.115
B18: 2.3 | C18: Long-term borrowings
C19: Unsecured loans
A20: Loan - Samartha Raghava Nagabhushanam | C20: ="From partner - "&Master!B22 -> From partner - Samartha Raghava Nagabhushanam | D20: =SUMIFS(TB!$G:$G,TB!$I:$I,$A20) -> 24806.8 | E20: =SUMIFS(TB!$H:$H,TB!$I:$I,$A20) -> 7806.8
A21: Loan - Manasa | C21: From others - Manasa | D21: =SUMIFS(TB!$G:$G,TB!$I:$I,$A21) -> 1701.8 | E21: =SUMIFS(TB!$H:$H,TB!$I:$I,$A21) -> 0
C22: Total | D22: =SUM(D20:D21) -> 26508.6 | E22: =SUM(E20:E21) -> 7806.8
B24: 2.4 | C24: Trade payables
C26: Outstanding dues of;
A27: Trade Payables - MSME | C27: (a) micro enterprises and small enterprises | D27: =SUMIFS(TB!$G:$G,TB!$I:$I,$A27) -> 0 | E27: =SUMIFS(TB!$H:$H,TB!$I:$I,$A27) -> 0
A28: Trade Payables - Others | C28: (b) other than micro enterprises and small enterprises | D28: =SUMIFS(TB!$G:$G,TB!$I:$I,$A28) -> 5483.2048 | E28: =SUMIFS(TB!$H:$H,TB!$I:$I,$A28) -> 2280
C30: Total | D30: =SUM(D27:D28) -> 5483.2048 | E30: =SUM(E27:E28) -> 2280
B32: 2.5 | C32: Other current liabilities
C33: Statutory dues
A34: TDS Payable 194J | C34: TDS payable (Section 194J) | D34: =SUMIFS(TB!$G:$G,TB!$I:$I,$A34) -> 217.6 | E34: =SUMIFS(TB!$H:$H,TB!$I:$I,$A34) -> 350
A35: GST Payable | C35: GST payable | D35: =SUMIFS(TB!$G:$G,TB!$I:$I,$A35) -> 75.0541 | E35: =SUMIFS(TB!$H:$H,TB!$I:$I,$A35) -> 0
C36: Others
A37: Book overdraft - Kotak Mahindra Bank | C37: Book overdraft - Kotak Mahindra Bank (credit balance as per books) | D37: =SUMIFS(TB!$G:$G,TB!$I:$I,$A37) -> 25.9305 | E37: =SUMIFS(TB!$H:$H,TB!$I:$I,$A37) -> 0
C39: Total | D39: =SUM(D34:D37) -> 318.5846 | E39: =SUM(E34:E37) -> 350
B41: 2.6 | C41: Cash and cash equivalents
A43: Cash in hand | C43: Cash in hand | D43: =SUMIFS(TB!$G:$G,TB!$I:$I,$A43) -> 207.542 | E43: =SUMIFS(TB!$H:$H,TB!$I:$I,$A43) -> 0
A44: Bank - Kotak Mahindra Bank | C44: Balances with banks - Kotak Mahindra Bank (current account) | D44: =SUMIFS(TB!$G:$G,TB!$I:$I,$A44) -> 0 | E44: =SUMIFS(TB!$H:$H,TB!$I:$I,$A44) -> 127.6848
C45: Total | D45: =SUM(D43:D44) -> 207.542 | E45: =SUM(E43:E44) -> 127.6848
B47: 2.7 | C47: Short-term loans and advances
C48: Advances to suppliers / consultants (debit balances in Sundry Creditors)
A49: Advance - Mangala | C49: Mangala | D49: =SUMIFS(TB!$G:$G,TB!$I:$I,$A49) -> 150 | E49: =SUMIFS(TB!$H:$H,TB!$I:$I,$A49) -> 0
A50: Advance - Sriguru P V | C50: Sriguru P V | D50: =SUMIFS(TB!$G:$G,TB!$I:$I,$A50) -> 200 | E50: =SUMIFS(TB!$H:$H,TB!$I:$I,$A50) -> 0
A51: Advance - Subodh Kumar Mishra | C51: Subodh Kumar Mishra | D51: =SUMIFS(TB!$G:$G,TB!$I:$I,$A51) -> 1210 | E51: =SUMIFS(TB!$H:$H,TB!$I:$I,$A51) -> 0
A52: Advance - Swami Gangaram | C52: Swami Gangaram | D52: =SUMIFS(TB!$G:$G,TB!$I:$I,$A52) -> 25 | E52: =SUMIFS(TB!$H:$H,TB!$I:$I,$A52) -> 0
A53: Advance - Yuvaraj | C53: Yuvaraj | D53: =SUMIFS(TB!$G:$G,TB!$I:$I,$A53) -> 150 | E53: =SUMIFS(TB!$H:$H,TB!$I:$I,$A53) -> 0
C55: Total | D55: =SUM(D49:D53) -> 1735 | E55: =SUM(E49:E53) -> 0
B57: 2.8 | C57: Other current assets
C58: Balances with government authorities
A59: Input CGST | C59: Input CGST 9% | D59: =SUMIFS(TB!$G:$G,TB!$I:$I,$A59) -> 28.2094 | E59: =SUMIFS(TB!$H:$H,TB!$I:$I,$A59) -> 0
A60: Input SGST | C60: Input SGST 9% | D60: =SUMIFS(TB!$G:$G,TB!$I:$I,$A60) -> 28.2094 | E60: =SUMIFS(TB!$H:$H,TB!$I:$I,$A60) -> 0
C62: Total | D62: =SUM(D59:D60) -> 56.4188 | E62: =SUM(E59:E60) -> 0
B64: 2.9 | C64: Revenue from operations
A66: B2C Sales | C66: B2C Sales | D66: =SUMIFS(TB!$G:$G,TB!$I:$I,$A66) -> 10593.635 | E66: =SUMIFS(TB!$H:$H,TB!$I:$I,$A66) -> 0
C68: Total | D68: =SUM(D66:D66) -> 10593.635 | E68: =SUM(E66:E66) -> 0
B70: 2.10 | C70: Other expenses
A72: Accomodation and Hotel Expenses | C72: Accommodation and Hotel Expenses | D72: =SUMIFS(TB!$G:$G,TB!$I:$I,$A72) -> 175.1 | E72: =SUMIFS(TB!$H:$H,TB!$I:$I,$A72) -> 0
A73: Advertisement Campaining Cost IGST | C73: Advertisement Campaigning Cost | D73: =SUMIFS(TB!$G:$G,TB!$I:$I,$A73) -> 4106.8535 | E73: =SUMIFS(TB!$H:$H,TB!$I:$I,$A73) -> 0
A74: Bank Charges | C74: Bank Charges | D74: =SUMIFS(TB!$G:$G,TB!$I:$I,$A74) -> 8.8063 | E74: =SUMIFS(TB!$H:$H,TB!$I:$I,$A74) -> 3.1152
A75: Branding Expenses | C75: Branding Expenses | D75: =SUMIFS(TB!$G:$G,TB!$I:$I,$A75) -> 191 | E75: =SUMIFS(TB!$H:$H,TB!$I:$I,$A75) -> 0
A76: Conveyance | C76: Conveyance | D76: =SUMIFS(TB!$G:$G,TB!$I:$I,$A76) -> 253.73 | E76: =SUMIFS(TB!$H:$H,TB!$I:$I,$A76) -> 0
A77: Data Infrastructure (GST) | C77: Data Infrastructure (GST) | D77: =SUMIFS(TB!$G:$G,TB!$I:$I,$A77) -> 262.2364 | E77: =SUMIFS(TB!$H:$H,TB!$I:$I,$A77) -> 0
A78: Design and Development | C78: Design and Development | D78: =SUMIFS(TB!$G:$G,TB!$I:$I,$A78) -> 700 | E78: =SUMIFS(TB!$H:$H,TB!$I:$I,$A78) -> 0
A79: Employer Professional Tax | C79: Employer Professional Tax | D79: =SUMIFS(TB!$G:$G,TB!$I:$I,$A79) -> 0 | E79: =SUMIFS(TB!$H:$H,TB!$I:$I,$A79) -> 25
A80: GST Late File Fees | C80: GST Late Filing Fees | D80: =SUMIFS(TB!$G:$G,TB!$I:$I,$A80) -> 0.2 | E80: =SUMIFS(TB!$H:$H,TB!$I:$I,$A80) -> 0
A81: Interest on TDS | C81: Interest on TDS | D81: =SUMIFS(TB!$G:$G,TB!$I:$I,$A81) -> 21.64 | E81: =SUMIFS(TB!$H:$H,TB!$I:$I,$A81) -> 7.8
A82: Internship Charges | C82: Internship Charges | D82: =SUMIFS(TB!$G:$G,TB!$I:$I,$A82) -> 120 | E82: =SUMIFS(TB!$H:$H,TB!$I:$I,$A82) -> 0
A83: Local Travel and Conveyance | C83: Local Travel and Conveyance | D83: =SUMIFS(TB!$G:$G,TB!$I:$I,$A83) -> 1774.17 | E83: =SUMIFS(TB!$H:$H,TB!$I:$I,$A83) -> 0
... A99: Web Site Development Expenses | C99: Website Development Expenses | D99: =SUMIFS(TB!$G:$G,TB!$I:$I,$A99) -> 100 | E99: =SUMIFS(TB!$H:$H,TB!$I:$I,$A99) -> 1250
C105: Total | D105: =SUM(D72:D99) -> 30595.949 | E105: =SUM(E72:E99) -> 11209.115

Sheet 2.11-2.12
A1: ='2.2 - 2.10'!B1 -> DAIVBHARATHI TECHNOLOGIES LLP
A2: ='2.2 - 2.10'!B2 -> LLPIN: [TO BE PROVIDED]
A3: =Master!B3 -> No 63, 1st Floor, 1st Main, 7th Block, Koramangala VI Block, Bangalore 560095
A4: ='2.2 - 2.10'!B4 -> 2. NOTES FORMING PART OF THE FINANCIAL STATEMENTS FOR THE YEAR ENDED MARCH 31, 2026
A6: 2.11 Related Party Disclosures
A8: a. Designated Partners / Key Management Personnel:
A10: Sl No | B10: Name of the Party | D10: Nature of relationship
A11: 1 | B11: =Master!B22 -> Samartha Raghava Nagabhushanam | D11: Designated Partner
A12: =+A11+1 -> 2 | B12: =Master!B26 -> [To be provided] | D12: Designated Partner
A14: b. Related Party Transactions and Balances: | E14: =Master!B32 -> (Amount in ₹ '00)
A16: Sl.No. | B16: Nature of transaction | D16: For the year ended | E16: For the year ended
D17: =PROPER(Master!B33) -> March 31, 2026 | E17: =PROPER(Master!B34) -> March 31, 2025
A18: 1 | B18: Partners' capital contribution (closing balance)
B19: =B11 -> Samartha Raghava Nagabhushanam | D19: ='2.1'!D11 -> 900 | E19: ='2.1'!E11 -> 900
A21: 2 | B21: Unsecured loan from partner (closing balance)
B22: =B11 -> Samartha Raghava Nagabhushanam | D22: ='2.2 - 2.10'!D20 -> 24806.8 | E22: ='2.2 - 2.10'!E20 -> 7806.8
A24: 3 | B24: Unsecured loan from partner - net amount received during the year
B25: =B11 -> Samartha Raghava Nagabhushanam | D25: =D22-E22 -> 17000 | E25: =E22-0 -> 7806.8
A27: No interest on the loan from the partner and no remuneration to partners has been charged in the books for the year (previous year: Nil). The previous-year figure of net loan received is stated on the basis that no opening balances appear in the Trial Balance for 2024-25.
A29: 2.12 - Previous period figures
A30: Previous year's figures have been regrouped / reclassified wherever necessary to conform to the current year's presentation.
A32: As per our report attached | C32: For and on behalf of the Partners of
A33: ="For "&Master!B16 -> For [To be provided] | C33: =Master!B2 -> Daivbharathi Technologies LLP
A34: ="(FRN: "&Master!B17&")" -> (FRN: [To be provided])
A38: =UPPER(Master!B13) -> [TO BE PROVIDED] | C38: =UPPER(Master!B22) -> SAMARTHA RAGHAVA NAGABHUSHANAM | D38: =UPPER(Master!B26) -> [TO BE PROVIDED]
A39: =PROPER(Master!B14) -> [To Be Provided] | C39: Designated Partner | D39: =C39 -> Designated Partner
A40: ="Membership No. "&Master!B15 -> Membership No. [To be provided] | C40: ="DPIN: "&Master!B23 -> DPIN: [To be provided] | D40: ="DPIN: "&Master!B27 -> DPIN: [To be provided]
A41: ="UDIN: "&Master!B18 -> UDIN: [To be provided]
A42: =Master!B19 -> [To be provided] | C42: =Master!B24 -> [To be provided] | D42: =Master!B28 -> [To be provided]
A43: =Master!B20 -> [To be provided] | C43: =Master!B25 -> [To be provided] | D43: =Master!B29 -> [To be provided]

Sheet Flags
B1: ITEMS REQUIRING CLARIFICATION / CONFIRMATION - NOT ASSUMED IN THE FINANCIAL STATEMENTS
B2: =Master!B2&" - FY "&Master!B5 -> Daivbharathi Technologies LLP - FY 2025-26
A4: # | B4: Area | C4: Observation (as per Trial Balance) | D4: Information required / treatment adopted
A5: 1 | B5: Period | C5: The FY 2025-26 Trial Balance exported from Tally covers 1-Apr-25 to 23-Mar-26, not the full year to 31-Mar-26. | D5: Statements are presented as at March 31, 2026 (FY 2025-26) as instructed. Transactions from 24-Mar-26 to 31-Mar-26 (if any) are not included. A TB to 31-Mar-26 should be re-exported and pasted into the TB sheet.
A6: 2 | B6: Entity / partners | C6: Only one partner capital account appears in the TB (Samartha R .N - Captial Account, Rs 90,000). An LLP must have at least two partners. | D6: Second designated partner name, DPIN, capital (if any) and profit-sharing ratio are required. Placeholders are in the Master sheet (yellow cells). Note 2.1(D) currently shows 100% contribution by the one partner in the TB.
A7: 3 | B7: Entity details | C7: LLPIN, PAN, LLP Agreement terms, incorporation date, auditor name/firm/FRN/membership no./UDIN, signing dates and places are not available in the TB. | D7: Fill the yellow cells in the Master sheet; all headers and signature blocks are linked to them. Note: statutory audit of an LLP is mandatory only if turnover exceeds Rs 40 lakh or contribution exceeds Rs 25 lakh; neither threshold is met per the TB, so confirm whether an auditor block is required.
A8: 4 | B8: Format | C8: The reference (Checkaro) is a Private Limited Company under Schedule III. The entity here is an LLP. | D8: Layout, fonts, rounding and note structure follow the reference exactly. Captions have been changed only where the entity type dictates: Share capital -> Partners' capital; Shareholder's funds -> Partners' funds; Board of Directors/Director/DIN -> Partners/Designated Partner/DPIN. Earnings per share and promoter shareholding (not applicable to an LLP) are omitted.
A9: 5 | B9: Bank | C9: Kotak Mahindra Bank ledger has a CREDIT balance of Rs 2,593.05 at 23-Mar-26 (Dr 12,768.48 at 31-Mar-25). | D9: A credit bank balance cannot be shown as cash. Presented as "Book overdraft - Kotak Mahindra Bank" under Other current liabilities (Note 2.5). Confirm against bank statement / BRS whether this is an actual overdraft or unrecorded receipts / timing.
A10: 6 | B10: Sundry creditors - debit balances | C10: Five Sundry Creditor ledgers have DEBIT balances totalling Rs 1,73,500 (Mangala 15,000; Sriguru P V 20,000; Subodh Kumar Mishra 1,21,000; Swami Gangaram 2,500; Yuvaraj 15,000). | D10: Presented as advances to suppliers/consultants under Short-term loans and advances (Note 2.7), not netted against payables. Confirm they are genuine advances and not unrecorded bills or payments posted to wrong ledgers.
A11: 7 | B11: Unsecured loans | C11: Loans (Liability): Samartha Raghava Nagabhushanam Rs 24,80,680 (PY 7,80,680) and Manasa Rs 1,70,180 (PY Nil). No repayment terms, interest or tenure in the TB. | D11: Classified as Long-term borrowings (Note 2.3), following the reference mapping of Directors Loan -> Long-term borrowings. Confirm tenure (if repayable within 12 months they belong under Short-term borrowings), interest (none charged in TB) and the relationship of Manasa (related party?).
A12: 8 | B12: Related parties | C12: Partner Samartha Raghava Nagabhushanam: capital Rs 90,000; loan closing Rs 24,80,680; net loan received during FY 25-26 Rs 17,00,000 (closing less PY closing). Many creditors are individuals grouped as "Consultants". | D12: Only the partner is disclosed as related party (Note 2.11). Gross loan receipts/repayments are not determinable from a TB (only net movement). Confirm whether any consultant/creditor (e.g. Madhavi K Rs 90,000, Sathyanarayana Bhat Rs 64,590) or lender Manasa is a relative of a partner.
A13: 9 | B13: Trade payables - MSME | C13: Sundry Creditors (credit balances) Rs 5,48,320.48 (PY 2,28,000). MSME status of suppliers is not in the TB. | D13: Entire amount shown under "other than micro and small enterprises" pending MSME confirmation (Note 2.4). Schedule III ageing schedule is not prepared: due-date information is not in a TB (and Schedule III does not apply to an LLP).
A14: 10 | B14: GST | C14: GST Payable Rs 7,505.41 (credit) and Input CGST Rs 2,820.94 + Input SGST Rs 2,820.94 (debit) exist as separate ledgers. | D14: Presented gross: GST payable under statutory dues (Note 2.5) and input credits under Other current assets (Note 2.8). Confirm with GSTR-3B / electronic credit ledger whether they should be set off and shown net.
A15: 11 | B15: Expense classification | C15: All expenses are grouped by Tally under "Indirect Expenses". Pooja Expenses Rs 9,59,127.50 and Professional Charges Rs 10,08,252 together exceed revenue of Rs 10,59,363.54. Staff Welfare Rs 7,681 / Internship Charges Rs 12,000 are employee-related; Bank Charges Rs 880.63 could be finance cost. | D15: All expenses are presented under a single "Other expenses" note (2.10) exactly as grouped in Tally, as in the reference. Confirm whether Pooja Expenses are direct cost of services and whether employee-benefit / finance-cost lines should be shown separately.
A16: 12 | B16: Pre-incorporation expenses | C16: Pre-incorporation Expenses Rs 36,000 in FY 25-26 in addition to Rs 4,79,320 in FY 24-25. | D16: Charged to P&L as per TB. Confirm the nature of the FY 25-26 amount (second year after incorporation) and whether any amount should be treated differently.
... A24: 20 | B24: Reference sheets not carried | C24: Reference workbook contains hidden company income-tax working sheets (IT Depn, IT Comp, DTA, MAT, ARI) and a hidden trade-payables ageing sheet, all with reference errors and specific to a company. | D24: Not reproduced (MAT, EPS, Schedule III ratios and ageing do not apply to an LLP; deferred tax not computed). Master and TB sheets are kept visible here so the mapping can be reviewed; hide them for printing if desired.
